cohere_aws/__init__.py
cohere_aws/client.py
cohere_aws/core/__init__.py
cohere_aws/core/api_error.py
cohere_aws/core/client_wrapper.py
cohere_aws/core/datetime_utils.py
cohere_aws/core/jsonable_encoder.py
cohere_aws/core/remove_none_from_dict.py
cohere_aws/environment.py
cohere_aws/py.typed
cohere_aws/resources/__init__.py
cohere_aws/resources/bedrock/__init__.py
cohere_aws/resources/bedrock/client.py
cohere_aws/resources/models/__init__.py
cohere_aws/resources/models/types/__init__.py
cohere_aws/resources/models/types/api_meta.py
cohere_aws/resources/models/types/api_meta_api_version.py
cohere_aws/resources/models/types/command_model.py
cohere_aws/resources/models/types/embed_model.py
cohere_aws/resources/models/types/embed_request_truncate.py
cohere_aws/resources/models/types/embed_response.py
cohere_aws/resources/models/types/generate_request_return_likelihoods.py
cohere_aws/resources/models/types/generate_request_truncate.py
cohere_aws/resources/models/types/generation.py
cohere_aws/resources/models/types/single_generation.py
cohere_aws/resources/models/types/single_generation_token_likelihoods_item.py
cohere_aws/resources/sagemaker/__init__.py
cohere_aws/resources/sagemaker/client.py
fern_cohere_aws-0.0.8.dist-info/METADATA
fern_cohere_aws-0.0.8.dist-info/WHEEL
fern_cohere_aws-0.0.8.dist-info/RECORD
