Metadata-Version: 2.1
Name: fern-cohere-aws
Version: 0.0.8
Summary: 
Requires-Python: >=3.7,<4.0
Classifier: Programming Language :: Python :: 3
Classifier: Programming Language :: Python :: 3.7
Classifier: Programming Language :: Python :: 3.8
Classifier: Programming Language :: Python :: 3.9
Classifier: Programming Language :: Python :: 3.10
Classifier: Programming Language :: Python :: 3.11
Requires-Dist: boto3 (>=1.28.57)
Requires-Dist: botocore (>=1.31.57)
Requires-Dist: httpx (>=0.21.2)
Requires-Dist: pydantic (>=1.9.2,<2.5.0)
